q2terminal/__init__.py
q2terminal/q2terminal.py
q2terminal/version.py
q2terminal-0.1.17.dist-info/METADATA
q2terminal-0.1.17.dist-info/WHEEL
q2terminal-0.1.17.dist-info/RECORD
