Metadata-Version: 2.1
Name: q2terminal
Version: 0.1.17
Summary: 
Author: Andrei Puchko
Author-email: andrei.puchko@gmx.de
Requires-Python: >=3.8.1
Classifier: Programming Language :: Python :: 3
Classifier: Programming Language :: Python :: 3.9
Classifier: Programming Language :: Python :: 3.10
Classifier: Programming Language :: Python :: 3.11
